MANIFEST.in
requirements.txt
setup.py
anarcho/__init__.py
anarcho/access_manager.py
anarcho/anarcho_cherry.py
anarcho/apk_helper.py
anarcho/ipa_helper.py
anarcho/ipin.py
anarcho/view_utils.py
anarcho.egg-info/PKG-INFO
anarcho.egg-info/SOURCES.txt
anarcho.egg-info/dependency_links.txt
anarcho.egg-info/entry_points.txt
anarcho.egg-info/not-zip-safe
anarcho.egg-info/requires.txt
anarcho.egg-info/top_level.txt
anarcho/models/__init__.py
anarcho/models/application.py
anarcho/models/build.py
anarcho/models/token.py
anarcho/models/track.py
anarcho/models/user.py
anarcho/models/user_app.py
anarcho/routes/__init__.py
anarcho/routes/apps.py
anarcho/routes/auth.py
anarcho/routes/build.py
anarcho/routes/general.py
anarcho/routes/team.py
anarcho/routes/tracking.py
anarcho/routes/upload.py
anarcho/serializer/__init__.py
anarcho/static/.htaccess
anarcho/static/404.html
anarcho/static/favicon.ico
anarcho/static/index.html
anarcho/static/robots.txt
anarcho/static/bower_components/zeroclipboard/dist/ZeroClipboard.swf
anarcho/static/fonts/logo_font.eot
anarcho/static/fonts/logo_font.svg
anarcho/static/fonts/logo_font.ttf
anarcho/static/fonts/logo_font.woff
anarcho/static/fonts/logo_font.woff2
anarcho/static/images/button-add.f424544f.png
anarcho/static/images/gear_icon.022f8e1f.png
anarcho/static/images/gear_icon_hovered.d76d81f4.png
anarcho/static/images/icon_apple.3270d7c9.png
anarcho/static/images/icon_droid.f2902d36.png
anarcho/static/images/loader.4c0ac5d4.gif
anarcho/static/images/logo.6db6798c.png
anarcho/static/scripts/oldieshim.ff90b0fb.js
anarcho/static/scripts/scripts.5cfc208c.js
anarcho/static/scripts/vendor.412d4de0.js
anarcho/static/styles/main.1fbd431f.css
anarcho/static/styles/vendor.8a6dcf07.css
anarcho/static/views/app_detail.html
anarcho/static/views/app_settings.html
anarcho/static/views/apps_list.html
anarcho/static/views/auth.html
anarcho/static/views/auth_login_form.html
anarcho/static/views/auth_reg_form.html
anarcho/static/views/build_details.html
anarcho/static/views/nav_bar.html
anarcho/static/views/new_app_modal.html
anarcho/static/views/settings_plugin_config_android.html
anarcho/static/views/settings_plugin_config_bash.html
