Metadata-Version: 1.0
Name: anarcho
Version: 0.5.3
Summary: Android artifact hosting service
Home-page: https://github.com/nrudenko/anarcho
Author: Nikolay Rudenko
Author-email: r.nikolay.e@gmail.com
License: MIT
Platform: any
